__init__.py
spatialcdr.py
spatialcdr-0.0.5.dist-info/LICENSE
spatialcdr-0.0.5.dist-info/METADATA
spatialcdr-0.0.5.dist-info/WHEEL
spatialcdr-0.0.5.dist-info/top_level.txt
spatialcdr-0.0.5.dist-info/RECORD
