Metadata-Version: 2.1
Name: spatialcdr
Version: 0.0.5
Summary: Spatial Transcriptomics
Author-email: Ashish_Swain <swainasish@gmail.com>
Maintainer-email: Shreshth Pal <shreshthpal@outlook.com>
License: Copyright (c) 2018 The Python Packaging Authority        
Project-URL: Homepage, https://github.com/swainasish/
Project-URL: Bug Tracker, https://github.com/swainasish/
Classifier: Programming Language :: Python :: 3
Classifier: License :: OSI Approved :: MIT License
Classifier: Operating System :: OS Independent
Requires-Python: >=3.6
License-File: LICENSE
Requires-Dist: pandas (>=1.3.5)
Requires-Dist: scikit-learn (==1.1.1)
Requires-Dist: numpy (>=1.17.3)
